[
    {
        "id": 1,
        "question": "What is the capital of France?",
        "options": ["Paris", "London", "Berlin", "Madrid"],
        "answer": "Paris"
    },
    {
        "id": 2,
        "question": "What is the largest planet in our solar system?",
        "options": ["Earth", "Mars", "Jupiter", "Saturn"],
        "answer": "Jupiter"
    },
    {
        "id": 3,
        "question": "Who wrote 'To Kill a Mockingbird'?",
        "options": ["Harper Lee", "Mark Twain", "Ernest Hemingway", "F. Scott Fitzgerald"],
        "answer": "Harper Lee"
    },
    {
        "id": 4,
        "question": "What is the chemical symbol for water?",
        "options": ["H2O", "O2", "CO2", "NaCl"],
        "answer": "H2O"
    }
]